python_carbon/__init__.py
python_carbon-0.2.0.dist-info/LICENSE.txt
python_carbon-0.2.0.dist-info/METADATA
python_carbon-0.2.0.dist-info/WHEEL
python_carbon-0.2.0.dist-info/top_level.txt
python_carbon-0.2.0.dist-info/RECORD
