Metadata-Version: 2.1
Name: python-carbon
Version: 0.2.0
Summary: PHP Carbon library adapted for python
Home-page: https://github.com/rogervila/python_carbon
Download-URL: https://github.com/rogervila/python_carbon/archive/0.2.0.tar.gz
Author: Roger Vilà
Author-email: rogervila@me.com
License: MIT
Keywords: php nesbot carbon,php carbon
Platform: UNKNOWN
Classifier: Development Status :: 5 - Production/Stable
Classifier: Intended Audience :: Developers
Classifier: Topic :: Software Development :: Build Tools
Classifier: License :: OSI Approved :: MIT License
Classifier: Programming Language :: Python :: 3.9
License-File: LICENSE.txt
Requires-Dist: python-dateutil (>=2)
